mypyref/__init__.py
mypyref/__main__.py
mypyref/handler.py
mypyref/xbar.py
mypyref-1.1.0.dist-info/METADATA
mypyref-1.1.0.dist-info/WHEEL
mypyref-1.1.0.dist-info/entry_points.txt
mypyref-1.1.0.dist-info/RECORD
