Metadata-Version: 2.1
Name: mypyref
Version: 1.1.0
Summary: Standard Python reference documentation in a local server
License: MIT
Author: Steampunk Wizard
Author-email: mypyref@steampunkwizard.ca
Requires-Python: >=3.11,<3.12
Classifier: License :: OSI Approved :: MIT License
Classifier: Programming Language :: Python :: 3
Classifier: Programming Language :: Python :: 3.11
Requires-Dist: wizlib (>=1.1,<1.2)
